README.md
setup.cfg
setup.py
eis/__init__.py
eis/commenting/__init__.py
eis/commenting/api_client.py
eis/commenting/configuration.py
eis/commenting/exceptions.py
eis/commenting/model_utils.py
eis/commenting/rest.py
eis/commenting/api/__init__.py
eis/commenting/api/comments_api.py
eis/commenting/api/health_api.py
eis/commenting/apis/__init__.py
eis/commenting/model/__init__.py
eis/commenting/model/comment_class.py
eis/commenting/model/create_comment_request_dto.py
eis/commenting/model/create_comment_response_class.py
eis/commenting/model/get_comment_response_class.py
eis/commenting/model/inline_response200.py
eis/commenting/model/inline_response503.py
eis/commenting/model/list_comment_response_class.py
eis/commenting/model/update_comment_request_dto.py
eis/commenting/model/update_comment_response_class.py
eis/commenting/models/__init__.py
eis_commenting.egg-info/PKG-INFO
eis_commenting.egg-info/SOURCES.txt
eis_commenting.egg-info/dependency_links.txt
eis_commenting.egg-info/requires.txt
eis_commenting.egg-info/top_level.txt
test/test_comment_class.py
test/test_comments_api.py
test/test_create_comment_request_dto.py
test/test_create_comment_response_class.py
test/test_get_comment_response_class.py
test/test_health_api.py
test/test_inline_response200.py
test/test_inline_response503.py
test/test_list_comment_response_class.py
test/test_update_comment_request_dto.py
test/test_update_comment_response_class.py