Metadata-Version: 2.1
Name: eis-commenting
Version: 1.2.0
Summary: EMIL Commentingservice
Home-page: UNKNOWN
Author: Contact us
Author-email: kontakt@emil.de
License: UNKNOWN
Keywords: OpenAPI,OpenAPI-Generator,EMIL Commentingservice
Platform: UNKNOWN
Requires-Python: >=3.6
